pypyrs-0.1.0.dist-info/METADATA
pypyrs-0.1.0.dist-info/WHEEL
pypyrs-0.1.0.dist-info/entry_points.txt
pypyrs/__init__.pyi
pypyrs/__init__.py
pypyrs/__main__.py
pypyrs/pypyrs.abi3.so
pypyrs-0.1.0.dist-info/RECORD
